README
setup.py
natural/__init__.py
natural/bank.py
natural/constant.py
natural/data.py
natural/date.py
natural/file.py
natural/language.py
natural/number.py
natural/phone.py
natural/size.py
natural/text.py
natural/util.py
will_natural.egg-info/PKG-INFO
will_natural.egg-info/SOURCES.txt
will_natural.egg-info/dependency_links.txt
will_natural.egg-info/requires.txt
will_natural.egg-info/top_level.txt