Metadata-Version: 1.0
Name: will-natural
Version: 0.2.1.1
Summary: Convert data to their natural (human-readable) format
Home-page: https://github.com/tehmaze/natural
Author: Steven Skoczen (fork only).  Original author is Wijnand Modderman-Lenstra
Author-email: steven@heywill.io
License: MIT
Keywords: natural data date file number size
Platform: UNKNOWN
